[{"dungeonId":"dungeon1","dungeonName":"testRoom","entities":[{"id":"entity0","type":"player","position":{"x":1,"y":1,"layer":0},"isInteractable":false,"attack":2,"health":10},{"id":"entity1","type":"zombie_toast_spawner","position":{"x":3,"y":4,"layer":0},"isInteractable":true},{"id":"entity2","type":"assassin","position":{"x":4,"y":4,"layer":0},"isInteractable":true},{"id":"entity3","type":"sword","position":{"x":2,"y":2,"layer":0},"isInteractable":false,"attack":3,"durability":5},{"id":"entity4","type":"mercenary","position":{"x":4,"y":1,"layer":0},"isInteractable":true,"attack":5,"health":4},{"id":"entity5","type":"mercenary","position":{"x":5,"y":5,"layer":0},"isInteractable":true,"attack":5,"health":4},{"id":"entity6","type":"invincibility_potion","position":{"x":1,"y":2,"layer":0},"isInteractable":false},{"id":"entity7","type":"wall","position":{"x":0,"y":0,"layer":0},"isInteractable":false},{"id":"entity8","type":"wall","position":{"x":1,"y":0,"layer":0},"isInteractable":false},{"id":"entity9","type":"wall","position":{"x":2,"y":0,"layer":0},"isInteractable":false},{"id":"entity10","type":"wall","position":{"x":3,"y":0,"layer":0},"isInteractable":false},{"id":"entity11","type":"wall","position":{"x":4,"y":0,"layer":0},"isInteractable":false},{"id":"entity12","type":"wall","position":{"x":5,"y":0,"layer":0},"isInteractable":false},{"id":"entity13","type":"wall","position":{"x":6,"y":0,"layer":0},"isInteractable":false},{"id":"entity14","type":"wall","position":{"x":7,"y":0,"layer":0},"isInteractable":false},{"id":"entity15","type":"wall","position":{"x":0,"y":1,"layer":0},"isInteractable":false},{"id":"entity16","type":"wall","position":{"x":0,"y":2,"layer":0},"isInteractable":false},{"id":"entity17","type":"wall","position":{"x":0,"y":3,"layer":0},"isInteractable":false},{"id":"entity18","type":"wall","position":{"x":0,"y":4,"layer":0},"isInteractable":false},{"id":"entity19","type":"wall","position":{"x":0,"y":5,"layer":0},"isInteractable":false},{"id":"entity20","type":"wall","position":{"x":0,"y":6,"layer":0},"isInteractable":false},{"id":"entity21","type":"wall","position":{"x":0,"y":10,"layer":0},"isInteractable":false},{"id":"entity22","type":"wall","position":{"x":1,"y":10,"layer":0},"isInteractable":false},{"id":"entity23","type":"wall","position":{"x":2,"y":10,"layer":0},"isInteractable":false},{"id":"entity24","type":"wall","position":{"x":3,"y":10,"layer":0},"isInteractable":false},{"id":"entity25","type":"wall","position":{"x":4,"y":10,"layer":0},"isInteractable":false},{"id":"entity26","type":"wall","position":{"x":5,"y":10,"layer":0},"isInteractable":false},{"id":"entity27","type":"wall","position":{"x":6,"y":10,"layer":0},"isInteractable":false},{"id":"entity28","type":"wall","position":{"x":7,"y":10,"layer":0},"isInteractable":false},{"id":"entity29","type":"wall","position":{"x":7,"y":6,"layer":0},"isInteractable":false},{"id":"entity30","type":"wall","position":{"x":7,"y":5,"layer":0},"isInteractable":false},{"id":"entity31","type":"wall","position":{"x":7,"y":4,"layer":0},"isInteractable":false},{"id":"entity32","type":"wall","position":{"x":7,"y":3,"layer":0},"isInteractable":false},{"id":"entity33","type":"wall","position":{"x":7,"y":2,"layer":0},"isInteractable":false},{"id":"entity34","type":"wall","position":{"x":7,"y":1,"layer":0},"isInteractable":false},{"id":"entity35","type":"wall","position":{"x":0,"y":7,"layer":0},"isInteractable":false},{"id":"entity36","type":"wall","position":{"x":7,"y":7,"layer":0},"isInteractable":false},{"id":"entity37","type":"wall","position":{"x":0,"y":8,"layer":0},"isInteractable":false},{"id":"entity38","type":"wall","position":{"x":7,"y":8,"layer":0},"isInteractable":false},{"id":"entity39","type":"wall","position":{"x":0,"y":9,"layer":0},"isInteractable":false},{"id":"entity40","type":"wall","position":{"x":7,"y":9,"layer":0},"isInteractable":false},{"id":"entity41","type":"treasure","position":{"x":6,"y":1,"layer":0},"isInteractable":false},{"id":"entity42","type":"treasure","position":{"x":5,"y":1,"layer":0},"isInteractable":false}],"inventory":[],"buildables":[],"goals":"","animations":[],"entityCounter":43,"tickCounter":0,"keyStatus":true,"invisibilityPotionCounter":0,"invincibilityPotionCounter":0},{"dungeonId":"dungeon1","dungeonName":"testRoom","entities":[{"id":"entity0","type":"player","position":{"x":2,"y":1,"layer":0},"isInteractable":false,"attack":2,"health":10},{"id":"entity1","type":"zombie_toast_spawner","position":{"x":3,"y":4,"layer":0},"isInteractable":true},{"id":"entity2","type":"assassin","position":{"x":4,"y":3,"layer":0},"isInteractable":true},{"id":"entity3","type":"sword","position":{"x":2,"y":2,"layer":0},"isInteractable":false,"attack":3,"durability":5},{"id":"entity4","type":"mercenary","position":{"x":3,"y":1,"layer":0},"isInteractable":true,"attack":5,"health":4},{"id":"entity5","type":"mercenary","position":{"x":5,"y":4,"layer":0},"isInteractable":true,"attack":5,"health":4},{"id":"entity6","type":"invincibility_potion","position":{"x":1,"y":2,"layer":0},"isInteractable":false},{"id":"entity7","type":"wall","position":{"x":0,"y":0,"layer":0},"isInteractable":false},{"id":"entity8","type":"wall","position":{"x":1,"y":0,"layer":0},"isInteractable":false},{"id":"entity9","type":"wall","position":{"x":2,"y":0,"layer":0},"isInteractable":false},{"id":"entity10","type":"wall","position":{"x":3,"y":0,"layer":0},"isInteractable":false},{"id":"entity11","type":"wall","position":{"x":4,"y":0,"layer":0},"isInteractable":false},{"id":"entity12","type":"wall","position":{"x":5,"y":0,"layer":0},"isInteractable":false},{"id":"entity13","type":"wall","position":{"x":6,"y":0,"layer":0},"isInteractable":false},{"id":"entity14","type":"wall","position":{"x":7,"y":0,"layer":0},"isInteractable":false},{"id":"entity15","type":"wall","position":{"x":0,"y":1,"layer":0},"isInteractable":false},{"id":"entity16","type":"wall","position":{"x":0,"y":2,"layer":0},"isInteractable":false},{"id":"entity17","type":"wall","position":{"x":0,"y":3,"layer":0},"isInteractable":false},{"id":"entity18","type":"wall","position":{"x":0,"y":4,"layer":0},"isInteractable":false},{"id":"entity19","type":"wall","position":{"x":0,"y":5,"layer":0},"isInteractable":false},{"id":"entity20","type":"wall","position":{"x":0,"y":6,"layer":0},"isInteractable":false},{"id":"entity21","type":"wall","position":{"x":0,"y":10,"layer":0},"isInteractable":false},{"id":"entity22","type":"wall","position":{"x":1,"y":10,"layer":0},"isInteractable":false},{"id":"entity23","type":"wall","position":{"x":2,"y":10,"layer":0},"isInteractable":false},{"id":"entity24","type":"wall","position":{"x":3,"y":10,"layer":0},"isInteractable":false},{"id":"entity25","type":"wall","position":{"x":4,"y":10,"layer":0},"isInteractable":false},{"id":"entity26","type":"wall","position":{"x":5,"y":10,"layer":0},"isInteractable":false},{"id":"entity27","type":"wall","position":{"x":6,"y":10,"layer":0},"isInteractable":false},{"id":"entity28","type":"wall","position":{"x":7,"y":10,"layer":0},"isInteractable":false},{"id":"entity29","type":"wall","position":{"x":7,"y":6,"layer":0},"isInteractable":false},{"id":"entity30","type":"wall","position":{"x":7,"y":5,"layer":0},"isInteractable":false},{"id":"entity31","type":"wall","position":{"x":7,"y":4,"layer":0},"isInteractable":false},{"id":"entity32","type":"wall","position":{"x":7,"y":3,"layer":0},"isInteractable":false},{"id":"entity33","type":"wall","position":{"x":7,"y":2,"layer":0},"isInteractable":false},{"id":"entity34","type":"wall","position":{"x":7,"y":1,"layer":0},"isInteractable":false},{"id":"entity35","type":"wall","position":{"x":0,"y":7,"layer":0},"isInteractable":false},{"id":"entity36","type":"wall","position":{"x":7,"y":7,"layer":0},"isInteractable":false},{"id":"entity37","type":"wall","position":{"x":0,"y":8,"layer":0},"isInteractable":false},{"id":"entity38","type":"wall","position":{"x":7,"y":8,"layer":0},"isInteractable":false},{"id":"entity39","type":"wall","position":{"x":0,"y":9,"layer":0},"isInteractable":false},{"id":"entity40","type":"wall","position":{"x":7,"y":9,"layer":0},"isInteractable":false},{"id":"entity41","type":"treasure","position":{"x":6,"y":1,"layer":0},"isInteractable":false},{"id":"entity42","type":"treasure","position":{"x":5,"y":1,"layer":0},"isInteractable":false}],"inventory":[],"buildables":[],"goals":"","animations":[{"when":"PostTick","entityId":"entity0","queue":["translate-x -1","translate-x 1, over 0.4s","sprite player"],"loop":false,"duration":-1.0}],"entityCounter":43,"tickCounter":1,"keyStatus":true,"invisibilityPotionCounter":0,"invincibilityPotionCounter":0},{"dungeonId":"dungeon1","dungeonName":"testRoom","entities":[{"id":"entity0","type":"player","position":{"x":3,"y":1,"layer":0},"isInteractable":false,"attack":2,"health":8},{"id":"entity1","type":"zombie_toast_spawner","position":{"x":3,"y":4,"layer":0},"isInteractable":true},{"id":"entity2","type":"assassin","position":{"x":4,"y":2,"layer":0},"isInteractable":true},{"id":"entity3","type":"sword","position":{"x":2,"y":2,"layer":0},"isInteractable":false,"attack":3,"durability":5},{"id":"entity5","type":"mercenary","position":{"x":5,"y":2,"layer":0},"isInteractable":true,"attack":5,"health":4},{"id":"entity6","type":"invincibility_potion","position":{"x":1,"y":2,"layer":0},"isInteractable":false},{"id":"entity7","type":"wall","position":{"x":0,"y":0,"layer":0},"isInteractable":false},{"id":"entity8","type":"wall","position":{"x":1,"y":0,"layer":0},"isInteractable":false},{"id":"entity9","type":"wall","position":{"x":2,"y":0,"layer":0},"isInteractable":false},{"id":"entity10","type":"wall","position":{"x":3,"y":0,"layer":0},"isInteractable":false},{"id":"entity11","type":"wall","position":{"x":4,"y":0,"layer":0},"isInteractable":false},{"id":"entity12","type":"wall","position":{"x":5,"y":0,"layer":0},"isInteractable":false},{"id":"entity13","type":"wall","position":{"x":6,"y":0,"layer":0},"isInteractable":false},{"id":"entity14","type":"wall","position":{"x":7,"y":0,"layer":0},"isInteractable":false},{"id":"entity15","type":"wall","position":{"x":0,"y":1,"layer":0},"isInteractable":false},{"id":"entity16","type":"wall","position":{"x":0,"y":2,"layer":0},"isInteractable":false},{"id":"entity17","type":"wall","position":{"x":0,"y":3,"layer":0},"isInteractable":false},{"id":"entity18","type":"wall","position":{"x":0,"y":4,"layer":0},"isInteractable":false},{"id":"entity19","type":"wall","position":{"x":0,"y":5,"layer":0},"isInteractable":false},{"id":"entity20","type":"wall","position":{"x":0,"y":6,"layer":0},"isInteractable":false},{"id":"entity21","type":"wall","position":{"x":0,"y":10,"layer":0},"isInteractable":false},{"id":"entity22","type":"wall","position":{"x":1,"y":10,"layer":0},"isInteractable":false},{"id":"entity23","type":"wall","position":{"x":2,"y":10,"layer":0},"isInteractable":false},{"id":"entity24","type":"wall","position":{"x":3,"y":10,"layer":0},"isInteractable":false},{"id":"entity25","type":"wall","position":{"x":4,"y":10,"layer":0},"isInteractable":false},{"id":"entity26","type":"wall","position":{"x":5,"y":10,"layer":0},"isInteractable":false},{"id":"entity27","type":"wall","position":{"x":6,"y":10,"layer":0},"isInteractable":false},{"id":"entity28","type":"wall","position":{"x":7,"y":10,"layer":0},"isInteractable":false},{"id":"entity29","type":"wall","position":{"x":7,"y":6,"layer":0},"isInteractable":false},{"id":"entity30","type":"wall","position":{"x":7,"y":5,"layer":0},"isInteractable":false},{"id":"entity31","type":"wall","position":{"x":7,"y":4,"layer":0},"isInteractable":false},{"id":"entity32","type":"wall","position":{"x":7,"y":3,"layer":0},"isInteractable":false},{"id":"entity33","type":"wall","position":{"x":7,"y":2,"layer":0},"isInteractable":false},{"id":"entity34","type":"wall","position":{"x":7,"y":1,"layer":0},"isInteractable":false},{"id":"entity35","type":"wall","position":{"x":0,"y":7,"layer":0},"isInteractable":false},{"id":"entity36","type":"wall","position":{"x":7,"y":7,"layer":0},"isInteractable":false},{"id":"entity37","type":"wall","position":{"x":0,"y":8,"layer":0},"isInteractable":false},{"id":"entity38","type":"wall","position":{"x":7,"y":8,"layer":0},"isInteractable":false},{"id":"entity39","type":"wall","position":{"x":0,"y":9,"layer":0},"isInteractable":false},{"id":"entity40","type":"wall","position":{"x":7,"y":9,"layer":0},"isInteractable":false},{"id":"entity41","type":"treasure","position":{"x":6,"y":1,"layer":0},"isInteractable":false},{"id":"entity42","type":"treasure","position":{"x":5,"y":1,"layer":0},"isInteractable":false}],"inventory":[{"id":"entity43","type":"one_ring"}],"buildables":[],"goals":"","animations":[{"when":"PostTick","entityId":"entity0","queue":["healthbar set 0.8, over 0.5s","healthbar tint 0x00ff00"],"loop":false,"duration":-1.0},{"when":"PostTick","entityId":"entity0","queue":["translate-x -1","translate-x 1, over 0.4s","sprite player"],"loop":false,"duration":-1.0}],"entityCounter":44,"tickCounter":2,"keyStatus":true,"invisibilityPotionCounter":0,"invincibilityPotionCounter":0},{"dungeonId":"dungeon1","dungeonName":"testRoom","entities":[{"id":"entity0","type":"player","position":{"x":4,"y":1,"layer":0},"isInteractable":false,"attack":2,"health":5},{"id":"entity1","type":"zombie_toast_spawner","position":{"x":3,"y":4,"layer":0},"isInteractable":true},{"id":"entity3","type":"sword","position":{"x":2,"y":2,"layer":0},"isInteractable":false,"attack":3,"durability":5},{"id":"entity5","type":"mercenary","position":{"x":5,"y":1,"layer":0},"isInteractable":true,"attack":5,"health":4},{"id":"entity6","type":"invincibility_potion","position":{"x":1,"y":2,"layer":0},"isInteractable":false},{"id":"entity7","type":"wall","position":{"x":0,"y":0,"layer":0},"isInteractable":false},{"id":"entity8","type":"wall","position":{"x":1,"y":0,"layer":0},"isInteractable":false},{"id":"entity9","type":"wall","position":{"x":2,"y":0,"layer":0},"isInteractable":false},{"id":"entity10","type":"wall","position":{"x":3,"y":0,"layer":0},"isInteractable":false},{"id":"entity11","type":"wall","position":{"x":4,"y":0,"layer":0},"isInteractable":false},{"id":"entity12","type":"wall","position":{"x":5,"y":0,"layer":0},"isInteractable":false},{"id":"entity13","type":"wall","position":{"x":6,"y":0,"layer":0},"isInteractable":false},{"id":"entity14","type":"wall","position":{"x":7,"y":0,"layer":0},"isInteractable":false},{"id":"entity15","type":"wall","position":{"x":0,"y":1,"layer":0},"isInteractable":false},{"id":"entity16","type":"wall","position":{"x":0,"y":2,"layer":0},"isInteractable":false},{"id":"entity17","type":"wall","position":{"x":0,"y":3,"layer":0},"isInteractable":false},{"id":"entity18","type":"wall","position":{"x":0,"y":4,"layer":0},"isInteractable":false},{"id":"entity19","type":"wall","position":{"x":0,"y":5,"layer":0},"isInteractable":false},{"id":"entity20","type":"wall","position":{"x":0,"y":6,"layer":0},"isInteractable":false},{"id":"entity21","type":"wall","position":{"x":0,"y":10,"layer":0},"isInteractable":false},{"id":"entity22","type":"wall","position":{"x":1,"y":10,"layer":0},"isInteractable":false},{"id":"entity23","type":"wall","position":{"x":2,"y":10,"layer":0},"isInteractable":false},{"id":"entity24","type":"wall","position":{"x":3,"y":10,"layer":0},"isInteractable":false},{"id":"entity25","type":"wall","position":{"x":4,"y":10,"layer":0},"isInteractable":false},{"id":"entity26","type":"wall","position":{"x":5,"y":10,"layer":0},"isInteractable":false},{"id":"entity27","type":"wall","position":{"x":6,"y":10,"layer":0},"isInteractable":false},{"id":"entity28","type":"wall","position":{"x":7,"y":10,"layer":0},"isInteractable":false},{"id":"entity29","type":"wall","position":{"x":7,"y":6,"layer":0},"isInteractable":false},{"id":"entity30","type":"wall","position":{"x":7,"y":5,"layer":0},"isInteractable":false},{"id":"entity31","type":"wall","position":{"x":7,"y":4,"layer":0},"isInteractable":false},{"id":"entity32","type":"wall","position":{"x":7,"y":3,"layer":0},"isInteractable":false},{"id":"entity33","type":"wall","position":{"x":7,"y":2,"layer":0},"isInteractable":false},{"id":"entity34","type":"wall","position":{"x":7,"y":1,"layer":0},"isInteractable":false},{"id":"entity35","type":"wall","position":{"x":0,"y":7,"layer":0},"isInteractable":false},{"id":"entity36","type":"wall","position":{"x":7,"y":7,"layer":0},"isInteractable":false},{"id":"entity37","type":"wall","position":{"x":0,"y":8,"layer":0},"isInteractable":false},{"id":"entity38","type":"wall","position":{"x":7,"y":8,"layer":0},"isInteractable":false},{"id":"entity39","type":"wall","position":{"x":0,"y":9,"layer":0},"isInteractable":false},{"id":"entity40","type":"wall","position":{"x":7,"y":9,"layer":0},"isInteractable":false},{"id":"entity41","type":"treasure","position":{"x":6,"y":1,"layer":0},"isInteractable":false},{"id":"entity42","type":"treasure","position":{"x":5,"y":1,"layer":0},"isInteractable":false}],"inventory":[{"id":"entity43","type":"one_ring"}],"buildables":[],"goals":"","animations":[{"when":"PostTick","entityId":"entity0","queue":["healthbar set 0.5, over 0.5s","healthbar tint 0x00ff00"],"loop":false,"duration":-1.0},{"when":"PostTick","entityId":"entity0","queue":["translate-x -1","translate-x 1, over 0.4s","sprite player"],"loop":false,"duration":-1.0}],"entityCounter":44,"tickCounter":3,"keyStatus":true,"invisibilityPotionCounter":0,"invincibilityPotionCounter":0},{"dungeonId":"dungeon1","dungeonName":"testRoom","entities":[{"id":"entity0","type":"player","position":{"x":4,"y":2,"layer":0},"isInteractable":false,"attack":2,"health":5},{"id":"entity1","type":"zombie_toast_spawner","position":{"x":3,"y":4,"layer":0},"isInteractable":true},{"id":"entity3","type":"sword","position":{"x":2,"y":2,"layer":0},"isInteractable":false,"attack":3,"durability":5},{"id":"entity5","type":"mercenary","position":{"x":4,"y":1,"layer":0},"isInteractable":true,"attack":5,"health":4},{"id":"entity6","type":"invincibility_potion","position":{"x":1,"y":2,"layer":0},"isInteractable":false},{"id":"entity7","type":"wall","position":{"x":0,"y":0,"layer":0},"isInteractable":false},{"id":"entity8","type":"wall","position":{"x":1,"y":0,"layer":0},"isInteractable":false},{"id":"entity9","type":"wall","position":{"x":2,"y":0,"layer":0},"isInteractable":false},{"id":"entity10","type":"wall","position":{"x":3,"y":0,"layer":0},"isInteractable":false},{"id":"entity11","type":"wall","position":{"x":4,"y":0,"layer":0},"isInteractable":false},{"id":"entity12","type":"wall","position":{"x":5,"y":0,"layer":0},"isInteractable":false},{"id":"entity13","type":"wall","position":{"x":6,"y":0,"layer":0},"isInteractable":false},{"id":"entity14","type":"wall","position":{"x":7,"y":0,"layer":0},"isInteractable":false},{"id":"entity15","type":"wall","position":{"x":0,"y":1,"layer":0},"isInteractable":false},{"id":"entity16","type":"wall","position":{"x":0,"y":2,"layer":0},"isInteractable":false},{"id":"entity17","type":"wall","position":{"x":0,"y":3,"layer":0},"isInteractable":false},{"id":"entity18","type":"wall","position":{"x":0,"y":4,"layer":0},"isInteractable":false},{"id":"entity19","type":"wall","position":{"x":0,"y":5,"layer":0},"isInteractable":false},{"id":"entity20","type":"wall","position":{"x":0,"y":6,"layer":0},"isInteractable":false},{"id":"entity21","type":"wall","position":{"x":0,"y":10,"layer":0},"isInteractable":false},{"id":"entity22","type":"wall","position":{"x":1,"y":10,"layer":0},"isInteractable":false},{"id":"entity23","type":"wall","position":{"x":2,"y":10,"layer":0},"isInteractable":false},{"id":"entity24","type":"wall","position":{"x":3,"y":10,"layer":0},"isInteractable":false},{"id":"entity25","type":"wall","position":{"x":4,"y":10,"layer":0},"isInteractable":false},{"id":"entity26","type":"wall","position":{"x":5,"y":10,"layer":0},"isInteractable":false},{"id":"entity27","type":"wall","position":{"x":6,"y":10,"layer":0},"isInteractable":false},{"id":"entity28","type":"wall","position":{"x":7,"y":10,"layer":0},"isInteractable":false},{"id":"entity29","type":"wall","position":{"x":7,"y":6,"layer":0},"isInteractable":false},{"id":"entity30","type":"wall","position":{"x":7,"y":5,"layer":0},"isInteractable":false},{"id":"entity31","type":"wall","position":{"x":7,"y":4,"layer":0},"isInteractable":false},{"id":"entity32","type":"wall","position":{"x":7,"y":3,"layer":0},"isInteractable":false},{"id":"entity33","type":"wall","position":{"x":7,"y":2,"layer":0},"isInteractable":false},{"id":"entity34","type":"wall","position":{"x":7,"y":1,"layer":0},"isInteractable":false},{"id":"entity35","type":"wall","position":{"x":0,"y":7,"layer":0},"isInteractable":false},{"id":"entity36","type":"wall","position":{"x":7,"y":7,"layer":0},"isInteractable":false},{"id":"entity37","type":"wall","position":{"x":0,"y":8,"layer":0},"isInteractable":false},{"id":"entity38","type":"wall","position":{"x":7,"y":8,"layer":0},"isInteractable":false},{"id":"entity39","type":"wall","position":{"x":0,"y":9,"layer":0},"isInteractable":false},{"id":"entity40","type":"wall","position":{"x":7,"y":9,"layer":0},"isInteractable":false},{"id":"entity41","type":"treasure","position":{"x":6,"y":1,"layer":0},"isInteractable":false},{"id":"entity42","type":"treasure","position":{"x":5,"y":1,"layer":0},"isInteractable":false}],"inventory":[{"id":"entity43","type":"one_ring"}],"buildables":[],"goals":"","animations":[{"when":"PostTick","entityId":"entity0","queue":["translate-y -1","translate-y 1, over 0.4s","sprite player"],"loop":false,"duration":-1.0}],"entityCounter":44,"tickCounter":4,"keyStatus":true,"invisibilityPotionCounter":0,"invincibilityPotionCounter":0},{"dungeonId":"dungeon1","dungeonName":"testRoom","entities":[{"id":"entity0","type":"player","position":{"x":3,"y":2,"layer":0},"isInteractable":false,"attack":2,"health":5},{"id":"entity1","type":"zombie_toast_spawner","position":{"x":3,"y":4,"layer":0},"isInteractable":true},{"id":"entity3","type":"sword","position":{"x":2,"y":2,"layer":0},"isInteractable":false,"attack":3,"durability":5},{"id":"entity5","type":"mercenary","position":{"x":4,"y":2,"layer":0},"isInteractable":true,"attack":5,"health":4},{"id":"entity6","type":"invincibility_potion","position":{"x":1,"y":2,"layer":0},"isInteractable":false},{"id":"entity7","type":"wall","position":{"x":0,"y":0,"layer":0},"isInteractable":false},{"id":"entity8","type":"wall","position":{"x":1,"y":0,"layer":0},"isInteractable":false},{"id":"entity9","type":"wall","position":{"x":2,"y":0,"layer":0},"isInteractable":false},{"id":"entity10","type":"wall","position":{"x":3,"y":0,"layer":0},"isInteractable":false},{"id":"entity11","type":"wall","position":{"x":4,"y":0,"layer":0},"isInteractable":false},{"id":"entity12","type":"wall","position":{"x":5,"y":0,"layer":0},"isInteractable":false},{"id":"entity13","type":"wall","position":{"x":6,"y":0,"layer":0},"isInteractable":false},{"id":"entity14","type":"wall","position":{"x":7,"y":0,"layer":0},"isInteractable":false},{"id":"entity15","type":"wall","position":{"x":0,"y":1,"layer":0},"isInteractable":false},{"id":"entity16","type":"wall","position":{"x":0,"y":2,"layer":0},"isInteractable":false},{"id":"entity17","type":"wall","position":{"x":0,"y":3,"layer":0},"isInteractable":false},{"id":"entity18","type":"wall","position":{"x":0,"y":4,"layer":0},"isInteractable":false},{"id":"entity19","type":"wall","position":{"x":0,"y":5,"layer":0},"isInteractable":false},{"id":"entity20","type":"wall","position":{"x":0,"y":6,"layer":0},"isInteractable":false},{"id":"entity21","type":"wall","position":{"x":0,"y":10,"layer":0},"isInteractable":false},{"id":"entity22","type":"wall","position":{"x":1,"y":10,"layer":0},"isInteractable":false},{"id":"entity23","type":"wall","position":{"x":2,"y":10,"layer":0},"isInteractable":false},{"id":"entity24","type":"wall","position":{"x":3,"y":10,"layer":0},"isInteractable":false},{"id":"entity25","type":"wall","position":{"x":4,"y":10,"layer":0},"isInteractable":false},{"id":"entity26","type":"wall","position":{"x":5,"y":10,"layer":0},"isInteractable":false},{"id":"entity27","type":"wall","position":{"x":6,"y":10,"layer":0},"isInteractable":false},{"id":"entity28","type":"wall","position":{"x":7,"y":10,"layer":0},"isInteractable":false},{"id":"entity29","type":"wall","position":{"x":7,"y":6,"layer":0},"isInteractable":false},{"id":"entity30","type":"wall","position":{"x":7,"y":5,"layer":0},"isInteractable":false},{"id":"entity31","type":"wall","position":{"x":7,"y":4,"layer":0},"isInteractable":false},{"id":"entity32","type":"wall","position":{"x":7,"y":3,"layer":0},"isInteractable":false},{"id":"entity33","type":"wall","position":{"x":7,"y":2,"layer":0},"isInteractable":false},{"id":"entity34","type":"wall","position":{"x":7,"y":1,"layer":0},"isInteractable":false},{"id":"entity35","type":"wall","position":{"x":0,"y":7,"layer":0},"isInteractable":false},{"id":"entity36","type":"wall","position":{"x":7,"y":7,"layer":0},"isInteractable":false},{"id":"entity37","type":"wall","position":{"x":0,"y":8,"layer":0},"isInteractable":false},{"id":"entity38","type":"wall","position":{"x":7,"y":8,"layer":0},"isInteractable":false},{"id":"entity39","type":"wall","position":{"x":0,"y":9,"layer":0},"isInteractable":false},{"id":"entity40","type":"wall","position":{"x":7,"y":9,"layer":0},"isInteractable":false},{"id":"entity41","type":"treasure","position":{"x":6,"y":1,"layer":0},"isInteractable":false},{"id":"entity42","type":"treasure","position":{"x":5,"y":1,"layer":0},"isInteractable":false}],"inventory":[{"id":"entity43","type":"one_ring"}],"buildables":[],"goals":"","animations":[{"when":"PostTick","entityId":"entity0","queue":["translate-x 1","translate-x -1, over 0.4s","sprite player"],"loop":false,"duration":-1.0}],"entityCounter":44,"tickCounter":5,"keyStatus":true,"invisibilityPotionCounter":0,"invincibilityPotionCounter":0},{"dungeonId":"dungeon1","dungeonName":"testRoom","entities":[{"id":"entity0","type":"player","position":{"x":3,"y":1,"layer":0},"isInteractable":false,"attack":2,"health":5},{"id":"entity1","type":"zombie_toast_spawner","position":{"x":3,"y":4,"layer":0},"isInteractable":true},{"id":"entity3","type":"sword","position":{"x":2,"y":2,"layer":0},"isInteractable":false,"attack":3,"durability":5},{"id":"entity5","type":"mercenary","position":{"x":3,"y":2,"layer":0},"isInteractable":true,"attack":5,"health":4},{"id":"entity6","type":"invincibility_potion","position":{"x":1,"y":2,"layer":0},"isInteractable":false},{"id":"entity7","type":"wall","position":{"x":0,"y":0,"layer":0},"isInteractable":false},{"id":"entity8","type":"wall","position":{"x":1,"y":0,"layer":0},"isInteractable":false},{"id":"entity9","type":"wall","position":{"x":2,"y":0,"layer":0},"isInteractable":false},{"id":"entity10","type":"wall","position":{"x":3,"y":0,"layer":0},"isInteractable":false},{"id":"entity11","type":"wall","position":{"x":4,"y":0,"layer":0},"isInteractable":false},{"id":"entity12","type":"wall","position":{"x":5,"y":0,"layer":0},"isInteractable":false},{"id":"entity13","type":"wall","position":{"x":6,"y":0,"layer":0},"isInteractable":false},{"id":"entity14","type":"wall","position":{"x":7,"y":0,"layer":0},"isInteractable":false},{"id":"entity15","type":"wall","position":{"x":0,"y":1,"layer":0},"isInteractable":false},{"id":"entity16","type":"wall","position":{"x":0,"y":2,"layer":0},"isInteractable":false},{"id":"entity17","type":"wall","position":{"x":0,"y":3,"layer":0},"isInteractable":false},{"id":"entity18","type":"wall","position":{"x":0,"y":4,"layer":0},"isInteractable":false},{"id":"entity19","type":"wall","position":{"x":0,"y":5,"layer":0},"isInteractable":false},{"id":"entity20","type":"wall","position":{"x":0,"y":6,"layer":0},"isInteractable":false},{"id":"entity21","type":"wall","position":{"x":0,"y":10,"layer":0},"isInteractable":false},{"id":"entity22","type":"wall","position":{"x":1,"y":10,"layer":0},"isInteractable":false},{"id":"entity23","type":"wall","position":{"x":2,"y":10,"layer":0},"isInteractable":false},{"id":"entity24","type":"wall","position":{"x":3,"y":10,"layer":0},"isInteractable":false},{"id":"entity25","type":"wall","position":{"x":4,"y":10,"layer":0},"isInteractable":false},{"id":"entity26","type":"wall","position":{"x":5,"y":10,"layer":0},"isInteractable":false},{"id":"entity27","type":"wall","position":{"x":6,"y":10,"layer":0},"isInteractable":false},{"id":"entity28","type":"wall","position":{"x":7,"y":10,"layer":0},"isInteractable":false},{"id":"entity29","type":"wall","position":{"x":7,"y":6,"layer":0},"isInteractable":false},{"id":"entity30","type":"wall","position":{"x":7,"y":5,"layer":0},"isInteractable":false},{"id":"entity31","type":"wall","position":{"x":7,"y":4,"layer":0},"isInteractable":false},{"id":"entity32","type":"wall","position":{"x":7,"y":3,"layer":0},"isInteractable":false},{"id":"entity33","type":"wall","position":{"x":7,"y":2,"layer":0},"isInteractable":false},{"id":"entity34","type":"wall","position":{"x":7,"y":1,"layer":0},"isInteractable":false},{"id":"entity35","type":"wall","position":{"x":0,"y":7,"layer":0},"isInteractable":false},{"id":"entity36","type":"wall","position":{"x":7,"y":7,"layer":0},"isInteractable":false},{"id":"entity37","type":"wall","position":{"x":0,"y":8,"layer":0},"isInteractable":false},{"id":"entity38","type":"wall","position":{"x":7,"y":8,"layer":0},"isInteractable":false},{"id":"entity39","type":"wall","position":{"x":0,"y":9,"layer":0},"isInteractable":false},{"id":"entity40","type":"wall","position":{"x":7,"y":9,"layer":0},"isInteractable":false},{"id":"entity41","type":"treasure","position":{"x":6,"y":1,"layer":0},"isInteractable":false},{"id":"entity42","type":"treasure","position":{"x":5,"y":1,"layer":0},"isInteractable":false}],"inventory":[{"id":"entity43","type":"one_ring"}],"buildables":[],"goals":"","animations":[{"when":"PostTick","entityId":"entity0","queue":["translate-y 1","translate-y -1, over 0.4s","sprite player"],"loop":false,"duration":-1.0}],"entityCounter":44,"tickCounter":6,"keyStatus":true,"invisibilityPotionCounter":0,"invincibilityPotionCounter":0},{"dungeonId":"dungeon1","dungeonName":"testRoom","entities":[{"id":"entity0","type":"player","position":{"x":4,"y":1,"layer":0},"isInteractable":false,"attack":2,"health":5},{"id":"entity1","type":"zombie_toast_spawner","position":{"x":3,"y":4,"layer":0},"isInteractable":true},{"id":"entity3","type":"sword","position":{"x":2,"y":2,"layer":0},"isInteractable":false,"attack":3,"durability":5},{"id":"entity5","type":"mercenary","position":{"x":3,"y":1,"layer":0},"isInteractable":true,"attack":5,"health":4},{"id":"entity6","type":"invincibility_potion","position":{"x":1,"y":2,"layer":0},"isInteractable":false},{"id":"entity7","type":"wall","position":{"x":0,"y":0,"layer":0},"isInteractable":false},{"id":"entity8","type":"wall","position":{"x":1,"y":0,"layer":0},"isInteractable":false},{"id":"entity9","type":"wall","position":{"x":2,"y":0,"layer":0},"isInteractable":false},{"id":"entity10","type":"wall","position":{"x":3,"y":0,"layer":0},"isInteractable":false},{"id":"entity11","type":"wall","position":{"x":4,"y":0,"layer":0},"isInteractable":false},{"id":"entity12","type":"wall","position":{"x":5,"y":0,"layer":0},"isInteractable":false},{"id":"entity13","type":"wall","position":{"x":6,"y":0,"layer":0},"isInteractable":false},{"id":"entity14","type":"wall","position":{"x":7,"y":0,"layer":0},"isInteractable":false},{"id":"entity15","type":"wall","position":{"x":0,"y":1,"layer":0},"isInteractable":false},{"id":"entity16","type":"wall","position":{"x":0,"y":2,"layer":0},"isInteractable":false},{"id":"entity17","type":"wall","position":{"x":0,"y":3,"layer":0},"isInteractable":false},{"id":"entity18","type":"wall","position":{"x":0,"y":4,"layer":0},"isInteractable":false},{"id":"entity19","type":"wall","position":{"x":0,"y":5,"layer":0},"isInteractable":false},{"id":"entity20","type":"wall","position":{"x":0,"y":6,"layer":0},"isInteractable":false},{"id":"entity21","type":"wall","position":{"x":0,"y":10,"layer":0},"isInteractable":false},{"id":"entity22","type":"wall","position":{"x":1,"y":10,"layer":0},"isInteractable":false},{"id":"entity23","type":"wall","position":{"x":2,"y":10,"layer":0},"isInteractable":false},{"id":"entity24","type":"wall","position":{"x":3,"y":10,"layer":0},"isInteractable":false},{"id":"entity25","type":"wall","position":{"x":4,"y":10,"layer":0},"isInteractable":false},{"id":"entity26","type":"wall","position":{"x":5,"y":10,"layer":0},"isInteractable":false},{"id":"entity27","type":"wall","position":{"x":6,"y":10,"layer":0},"isInteractable":false},{"id":"entity28","type":"wall","position":{"x":7,"y":10,"layer":0},"isInteractable":false},{"id":"entity29","type":"wall","position":{"x":7,"y":6,"layer":0},"isInteractable":false},{"id":"entity30","type":"wall","position":{"x":7,"y":5,"layer":0},"isInteractable":false},{"id":"entity31","type":"wall","position":{"x":7,"y":4,"layer":0},"isInteractable":false},{"id":"entity32","type":"wall","position":{"x":7,"y":3,"layer":0},"isInteractable":false},{"id":"entity33","type":"wall","position":{"x":7,"y":2,"layer":0},"isInteractable":false},{"id":"entity34","type":"wall","position":{"x":7,"y":1,"layer":0},"isInteractable":false},{"id":"entity35","type":"wall","position":{"x":0,"y":7,"layer":0},"isInteractable":false},{"id":"entity36","type":"wall","position":{"x":7,"y":7,"layer":0},"isInteractable":false},{"id":"entity37","type":"wall","position":{"x":0,"y":8,"layer":0},"isInteractable":false},{"id":"entity38","type":"wall","position":{"x":7,"y":8,"layer":0},"isInteractable":false},{"id":"entity39","type":"wall","position":{"x":0,"y":9,"layer":0},"isInteractable":false},{"id":"entity40","type":"wall","position":{"x":7,"y":9,"layer":0},"isInteractable":false},{"id":"entity41","type":"treasure","position":{"x":6,"y":1,"layer":0},"isInteractable":false},{"id":"entity42","type":"treasure","position":{"x":5,"y":1,"layer":0},"isInteractable":false}],"inventory":[{"id":"entity43","type":"one_ring"}],"buildables":[],"goals":"","animations":[{"when":"PostTick","entityId":"entity0","queue":["translate-x -1","translate-x 1, over 0.4s","sprite player"],"loop":false,"duration":-1.0}],"entityCounter":44,"tickCounter":7,"keyStatus":true,"invisibilityPotionCounter":0,"invincibilityPotionCounter":0},{"dungeonId":"dungeon1","dungeonName":"testRoom","entities":[{"id":"entity1","type":"zombie_toast_spawner","position":{"x":3,"y":4,"layer":0},"isInteractable":true},{"id":"entity3","type":"sword","position":{"x":2,"y":2,"layer":0},"isInteractable":false,"attack":3,"durability":5},{"id":"entity5","type":"mercenary","position":{"x":3,"y":1,"layer":0},"isInteractable":true,"attack":5,"health":3},{"id":"entity6","type":"invincibility_potion","position":{"x":1,"y":2,"layer":0},"isInteractable":false},{"id":"entity7","type":"wall","position":{"x":0,"y":0,"layer":0},"isInteractable":false},{"id":"entity8","type":"wall","position":{"x":1,"y":0,"layer":0},"isInteractable":false},{"id":"entity9","type":"wall","position":{"x":2,"y":0,"layer":0},"isInteractable":false},{"id":"entity10","type":"wall","position":{"x":3,"y":0,"layer":0},"isInteractable":false},{"id":"entity11","type":"wall","position":{"x":4,"y":0,"layer":0},"isInteractable":false},{"id":"entity12","type":"wall","position":{"x":5,"y":0,"layer":0},"isInteractable":false},{"id":"entity13","type":"wall","position":{"x":6,"y":0,"layer":0},"isInteractable":false},{"id":"entity14","type":"wall","position":{"x":7,"y":0,"layer":0},"isInteractable":false},{"id":"entity15","type":"wall","position":{"x":0,"y":1,"layer":0},"isInteractable":false},{"id":"entity16","type":"wall","position":{"x":0,"y":2,"layer":0},"isInteractable":false},{"id":"entity17","type":"wall","position":{"x":0,"y":3,"layer":0},"isInteractable":false},{"id":"entity18","type":"wall","position":{"x":0,"y":4,"layer":0},"isInteractable":false},{"id":"entity19","type":"wall","position":{"x":0,"y":5,"layer":0},"isInteractable":false},{"id":"entity20","type":"wall","position":{"x":0,"y":6,"layer":0},"isInteractable":false},{"id":"entity21","type":"wall","position":{"x":0,"y":10,"layer":0},"isInteractable":false},{"id":"entity22","type":"wall","position":{"x":1,"y":10,"layer":0},"isInteractable":false},{"id":"entity23","type":"wall","position":{"x":2,"y":10,"layer":0},"isInteractable":false},{"id":"entity24","type":"wall","position":{"x":3,"y":10,"layer":0},"isInteractable":false},{"id":"entity25","type":"wall","position":{"x":4,"y":10,"layer":0},"isInteractable":false},{"id":"entity26","type":"wall","position":{"x":5,"y":10,"layer":0},"isInteractable":false},{"id":"entity27","type":"wall","position":{"x":6,"y":10,"layer":0},"isInteractable":false},{"id":"entity28","type":"wall","position":{"x":7,"y":10,"layer":0},"isInteractable":false},{"id":"entity29","type":"wall","position":{"x":7,"y":6,"layer":0},"isInteractable":false},{"id":"entity30","type":"wall","position":{"x":7,"y":5,"layer":0},"isInteractable":false},{"id":"entity31","type":"wall","position":{"x":7,"y":4,"layer":0},"isInteractable":false},{"id":"entity32","type":"wall","position":{"x":7,"y":3,"layer":0},"isInteractable":false},{"id":"entity33","type":"wall","position":{"x":7,"y":2,"layer":0},"isInteractable":false},{"id":"entity34","type":"wall","position":{"x":7,"y":1,"layer":0},"isInteractable":false},{"id":"entity35","type":"wall","position":{"x":0,"y":7,"layer":0},"isInteractable":false},{"id":"entity36","type":"wall","position":{"x":7,"y":7,"layer":0},"isInteractable":false},{"id":"entity37","type":"wall","position":{"x":0,"y":8,"layer":0},"isInteractable":false},{"id":"entity38","type":"wall","position":{"x":7,"y":8,"layer":0},"isInteractable":false},{"id":"entity39","type":"wall","position":{"x":0,"y":9,"layer":0},"isInteractable":false},{"id":"entity40","type":"wall","position":{"x":7,"y":9,"layer":0},"isInteractable":false},{"id":"entity41","type":"treasure","position":{"x":6,"y":1,"layer":0},"isInteractable":false},{"id":"entity42","type":"treasure","position":{"x":5,"y":1,"layer":0},"isInteractable":false},{"id":"entity0","type":"player","position":{"x":3,"y":1,"layer":0},"isInteractable":false,"attack":2,"health":10}],"inventory":[],"buildables":[],"goals":"","animations":[{"when":"PostTick","entityId":"entity0","queue":["healthbar set 0.0, over 0.5s","healthbar tint 0x00ff00"],"loop":false,"duration":-1.0},{"when":"PostTick","entityId":"entity0","queue":["translate-x 1","translate-x -1, over 0.4s","sprite player"],"loop":false,"duration":-1.0}],"entityCounter":44,"tickCounter":8,"keyStatus":true,"invisibilityPotionCounter":0,"invincibilityPotionCounter":0},{"dungeonId":"dungeon1","dungeonName":"testRoom","entities":[{"id":"entity1","type":"zombie_toast_spawner","position":{"x":3,"y":4,"layer":0},"isInteractable":true},{"id":"entity3","type":"sword","position":{"x":2,"y":2,"layer":0},"isInteractable":false,"attack":3,"durability":5},{"id":"entity5","type":"mercenary","position":{"x":3,"y":1,"layer":0},"isInteractable":true,"attack":5,"health":3},{"id":"entity6","type":"invincibility_potion","position":{"x":1,"y":2,"layer":0},"isInteractable":false},{"id":"entity7","type":"wall","position":{"x":0,"y":0,"layer":0},"isInteractable":false},{"id":"entity8","type":"wall","position":{"x":1,"y":0,"layer":0},"isInteractable":false},{"id":"entity9","type":"wall","position":{"x":2,"y":0,"layer":0},"isInteractable":false},{"id":"entity10","type":"wall","position":{"x":3,"y":0,"layer":0},"isInteractable":false},{"id":"entity11","type":"wall","position":{"x":4,"y":0,"layer":0},"isInteractable":false},{"id":"entity12","type":"wall","position":{"x":5,"y":0,"layer":0},"isInteractable":false},{"id":"entity13","type":"wall","position":{"x":6,"y":0,"layer":0},"isInteractable":false},{"id":"entity14","type":"wall","position":{"x":7,"y":0,"layer":0},"isInteractable":false},{"id":"entity15","type":"wall","position":{"x":0,"y":1,"layer":0},"isInteractable":false},{"id":"entity16","type":"wall","position":{"x":0,"y":2,"layer":0},"isInteractable":false},{"id":"entity17","type":"wall","position":{"x":0,"y":3,"layer":0},"isInteractable":false},{"id":"entity18","type":"wall","position":{"x":0,"y":4,"layer":0},"isInteractable":false},{"id":"entity19","type":"wall","position":{"x":0,"y":5,"layer":0},"isInteractable":false},{"id":"entity20","type":"wall","position":{"x":0,"y":6,"layer":0},"isInteractable":false},{"id":"entity21","type":"wall","position":{"x":0,"y":10,"layer":0},"isInteractable":false},{"id":"entity22","type":"wall","position":{"x":1,"y":10,"layer":0},"isInteractable":false},{"id":"entity23","type":"wall","position":{"x":2,"y":10,"layer":0},"isInteractable":false},{"id":"entity24","type":"wall","position":{"x":3,"y":10,"layer":0},"isInteractable":false},{"id":"entity25","type":"wall","position":{"x":4,"y":10,"layer":0},"isInteractable":false},{"id":"entity26","type":"wall","position":{"x":5,"y":10,"layer":0},"isInteractable":false},{"id":"entity27","type":"wall","position":{"x":6,"y":10,"layer":0},"isInteractable":false},{"id":"entity28","type":"wall","position":{"x":7,"y":10,"layer":0},"isInteractable":false},{"id":"entity29","type":"wall","position":{"x":7,"y":6,"layer":0},"isInteractable":false},{"id":"entity30","type":"wall","position":{"x":7,"y":5,"layer":0},"isInteractable":false},{"id":"entity31","type":"wall","position":{"x":7,"y":4,"layer":0},"isInteractable":false},{"id":"entity32","type":"wall","position":{"x":7,"y":3,"layer":0},"isInteractable":false},{"id":"entity33","type":"wall","position":{"x":7,"y":2,"layer":0},"isInteractable":false},{"id":"entity34","type":"wall","position":{"x":7,"y":1,"layer":0},"isInteractable":false},{"id":"entity35","type":"wall","position":{"x":0,"y":7,"layer":0},"isInteractable":false},{"id":"entity36","type":"wall","position":{"x":7,"y":7,"layer":0},"isInteractable":false},{"id":"entity37","type":"wall","position":{"x":0,"y":8,"layer":0},"isInteractable":false},{"id":"entity38","type":"wall","position":{"x":7,"y":8,"layer":0},"isInteractable":false},{"id":"entity39","type":"wall","position":{"x":0,"y":9,"layer":0},"isInteractable":false},{"id":"entity40","type":"wall","position":{"x":7,"y":9,"layer":0},"isInteractable":false},{"id":"entity41","type":"treasure","position":{"x":6,"y":1,"layer":0},"isInteractable":false},{"id":"entity42","type":"treasure","position":{"x":5,"y":1,"layer":0},"isInteractable":false},{"id":"entity0","type":"player","position":{"x":3,"y":2,"layer":0},"isInteractable":false,"attack":2,"health":10}],"inventory":[],"buildables":[],"goals":"","animations":[{"when":"PostTick","entityId":"entity0","queue":["translate-y -1","translate-y 1, over 0.4s","sprite player"],"loop":false,"duration":-1.0}],"entityCounter":44,"tickCounter":9,"keyStatus":true,"invisibilityPotionCounter":0,"invincibilityPotionCounter":0},{"dungeonId":"dungeon1","dungeonName":"testRoom","entities":[{"id":"entity1","type":"zombie_toast_spawner","position":{"x":3,"y":4,"layer":0},"isInteractable":true},{"id":"entity3","type":"sword","position":{"x":2,"y":2,"layer":0},"isInteractable":false,"attack":3,"durability":5},{"id":"entity6","type":"invincibility_potion","position":{"x":1,"y":2,"layer":0},"isInteractable":false},{"id":"entity7","type":"wall","position":{"x":0,"y":0,"layer":0},"isInteractable":false},{"id":"entity8","type":"wall","position":{"x":1,"y":0,"layer":0},"isInteractable":false},{"id":"entity9","type":"wall","position":{"x":2,"y":0,"layer":0},"isInteractable":false},{"id":"entity10","type":"wall","position":{"x":3,"y":0,"layer":0},"isInteractable":false},{"id":"entity11","type":"wall","position":{"x":4,"y":0,"layer":0},"isInteractable":false},{"id":"entity12","type":"wall","position":{"x":5,"y":0,"layer":0},"isInteractable":false},{"id":"entity13","type":"wall","position":{"x":6,"y":0,"layer":0},"isInteractable":false},{"id":"entity14","type":"wall","position":{"x":7,"y":0,"layer":0},"isInteractable":false},{"id":"entity15","type":"wall","position":{"x":0,"y":1,"layer":0},"isInteractable":false},{"id":"entity16","type":"wall","position":{"x":0,"y":2,"layer":0},"isInteractable":false},{"id":"entity17","type":"wall","position":{"x":0,"y":3,"layer":0},"isInteractable":false},{"id":"entity18","type":"wall","position":{"x":0,"y":4,"layer":0},"isInteractable":false},{"id":"entity19","type":"wall","position":{"x":0,"y":5,"layer":0},"isInteractable":false},{"id":"entity20","type":"wall","position":{"x":0,"y":6,"layer":0},"isInteractable":false},{"id":"entity21","type":"wall","position":{"x":0,"y":10,"layer":0},"isInteractable":false},{"id":"entity22","type":"wall","position":{"x":1,"y":10,"layer":0},"isInteractable":false},{"id":"entity23","type":"wall","position":{"x":2,"y":10,"layer":0},"isInteractable":false},{"id":"entity24","type":"wall","position":{"x":3,"y":10,"layer":0},"isInteractable":false},{"id":"entity25","type":"wall","position":{"x":4,"y":10,"layer":0},"isInteractable":false},{"id":"entity26","type":"wall","position":{"x":5,"y":10,"layer":0},"isInteractable":false},{"id":"entity27","type":"wall","position":{"x":6,"y":10,"layer":0},"isInteractable":false},{"id":"entity28","type":"wall","position":{"x":7,"y":10,"layer":0},"isInteractable":false},{"id":"entity29","type":"wall","position":{"x":7,"y":6,"layer":0},"isInteractable":false},{"id":"entity30","type":"wall","position":{"x":7,"y":5,"layer":0},"isInteractable":false},{"id":"entity31","type":"wall","position":{"x":7,"y":4,"layer":0},"isInteractable":false},{"id":"entity32","type":"wall","position":{"x":7,"y":3,"layer":0},"isInteractable":false},{"id":"entity33","type":"wall","position":{"x":7,"y":2,"layer":0},"isInteractable":false},{"id":"entity34","type":"wall","position":{"x":7,"y":1,"layer":0},"isInteractable":false},{"id":"entity35","type":"wall","position":{"x":0,"y":7,"layer":0},"isInteractable":false},{"id":"entity36","type":"wall","position":{"x":7,"y":7,"layer":0},"isInteractable":false},{"id":"entity37","type":"wall","position":{"x":0,"y":8,"layer":0},"isInteractable":false},{"id":"entity38","type":"wall","position":{"x":7,"y":8,"layer":0},"isInteractable":false},{"id":"entity39","type":"wall","position":{"x":0,"y":9,"layer":0},"isInteractable":false},{"id":"entity40","type":"wall","position":{"x":7,"y":9,"layer":0},"isInteractable":false},{"id":"entity41","type":"treasure","position":{"x":6,"y":1,"layer":0},"isInteractable":false},{"id":"entity42","type":"treasure","position":{"x":5,"y":1,"layer":0},"isInteractable":false},{"id":"entity0","type":"player","position":{"x":3,"y":1,"layer":0},"isInteractable":false,"attack":2,"health":9}],"inventory":[],"buildables":[],"goals":"","animations":[{"when":"PostTick","entityId":"entity0","queue":["healthbar set 0.9, over 0.5s","healthbar tint 0x00ff00"],"loop":false,"duration":-1.0},{"when":"PostTick","entityId":"entity0","queue":["translate-y 1","translate-y -1, over 0.4s","sprite player"],"loop":false,"duration":-1.0}],"entityCounter":44,"tickCounter":10,"keyStatus":true,"invisibilityPotionCounter":0,"invincibilityPotionCounter":0},{"dungeonId":"dungeon1","dungeonName":"testRoom","entities":[{"id":"entity1","type":"zombie_toast_spawner","position":{"x":3,"y":4,"layer":0},"isInteractable":true},{"id":"entity3","type":"sword","position":{"x":2,"y":2,"layer":0},"isInteractable":false,"attack":3,"durability":5},{"id":"entity6","type":"invincibility_potion","position":{"x":1,"y":2,"layer":0},"isInteractable":false},{"id":"entity7","type":"wall","position":{"x":0,"y":0,"layer":0},"isInteractable":false},{"id":"entity8","type":"wall","position":{"x":1,"y":0,"layer":0},"isInteractable":false},{"id":"entity9","type":"wall","position":{"x":2,"y":0,"layer":0},"isInteractable":false},{"id":"entity10","type":"wall","position":{"x":3,"y":0,"layer":0},"isInteractable":false},{"id":"entity11","type":"wall","position":{"x":4,"y":0,"layer":0},"isInteractable":false},{"id":"entity12","type":"wall","position":{"x":5,"y":0,"layer":0},"isInteractable":false},{"id":"entity13","type":"wall","position":{"x":6,"y":0,"layer":0},"isInteractable":false},{"id":"entity14","type":"wall","position":{"x":7,"y":0,"layer":0},"isInteractable":false},{"id":"entity15","type":"wall","position":{"x":0,"y":1,"layer":0},"isInteractable":false},{"id":"entity16","type":"wall","position":{"x":0,"y":2,"layer":0},"isInteractable":false},{"id":"entity17","type":"wall","position":{"x":0,"y":3,"layer":0},"isInteractable":false},{"id":"entity18","type":"wall","position":{"x":0,"y":4,"layer":0},"isInteractable":false},{"id":"entity19","type":"wall","position":{"x":0,"y":5,"layer":0},"isInteractable":false},{"id":"entity20","type":"wall","position":{"x":0,"y":6,"layer":0},"isInteractable":false},{"id":"entity21","type":"wall","position":{"x":0,"y":10,"layer":0},"isInteractable":false},{"id":"entity22","type":"wall","position":{"x":1,"y":10,"layer":0},"isInteractable":false},{"id":"entity23","type":"wall","position":{"x":2,"y":10,"layer":0},"isInteractable":false},{"id":"entity24","type":"wall","position":{"x":3,"y":10,"layer":0},"isInteractable":false},{"id":"entity25","type":"wall","position":{"x":4,"y":10,"layer":0},"isInteractable":false},{"id":"entity26","type":"wall","position":{"x":5,"y":10,"layer":0},"isInteractable":false},{"id":"entity27","type":"wall","position":{"x":6,"y":10,"layer":0},"isInteractable":false},{"id":"entity28","type":"wall","position":{"x":7,"y":10,"layer":0},"isInteractable":false},{"id":"entity29","type":"wall","position":{"x":7,"y":6,"layer":0},"isInteractable":false},{"id":"entity30","type":"wall","position":{"x":7,"y":5,"layer":0},"isInteractable":false},{"id":"entity31","type":"wall","position":{"x":7,"y":4,"layer":0},"isInteractable":false},{"id":"entity32","type":"wall","position":{"x":7,"y":3,"layer":0},"isInteractable":false},{"id":"entity33","type":"wall","position":{"x":7,"y":2,"layer":0},"isInteractable":false},{"id":"entity34","type":"wall","position":{"x":7,"y":1,"layer":0},"isInteractable":false},{"id":"entity35","type":"wall","position":{"x":0,"y":7,"layer":0},"isInteractable":false},{"id":"entity36","type":"wall","position":{"x":7,"y":7,"layer":0},"isInteractable":false},{"id":"entity37","type":"wall","position":{"x":0,"y":8,"layer":0},"isInteractable":false},{"id":"entity38","type":"wall","position":{"x":7,"y":8,"layer":0},"isInteractable":false},{"id":"entity39","type":"wall","position":{"x":0,"y":9,"layer":0},"isInteractable":false},{"id":"entity40","type":"wall","position":{"x":7,"y":9,"layer":0},"isInteractable":false},{"id":"entity41","type":"treasure","position":{"x":6,"y":1,"layer":0},"isInteractable":false},{"id":"entity42","type":"treasure","position":{"x":5,"y":1,"layer":0},"isInteractable":false},{"id":"entity0","type":"player","position":{"x":4,"y":1,"layer":0},"isInteractable":false,"attack":2,"health":9}],"inventory":[],"buildables":[],"goals":"","animations":[{"when":"PostTick","entityId":"entity0","queue":["translate-x -1","translate-x 1, over 0.4s","sprite player"],"loop":false,"duration":-1.0}],"entityCounter":44,"tickCounter":11,"keyStatus":true,"invisibilityPotionCounter":0,"invincibilityPotionCounter":0},{"dungeonId":"dungeon1","dungeonName":"testRoom","entities":[{"id":"entity1","type":"zombie_toast_spawner","position":{"x":3,"y":4,"layer":0},"isInteractable":true},{"id":"entity3","type":"sword","position":{"x":2,"y":2,"layer":0},"isInteractable":false,"attack":3,"durability":5},{"id":"entity6","type":"invincibility_potion","position":{"x":1,"y":2,"layer":0},"isInteractable":false},{"id":"entity7","type":"wall","position":{"x":0,"y":0,"layer":0},"isInteractable":false},{"id":"entity8","type":"wall","position":{"x":1,"y":0,"layer":0},"isInteractable":false},{"id":"entity9","type":"wall","position":{"x":2,"y":0,"layer":0},"isInteractable":false},{"id":"entity10","type":"wall","position":{"x":3,"y":0,"layer":0},"isInteractable":false},{"id":"entity11","type":"wall","position":{"x":4,"y":0,"layer":0},"isInteractable":false},{"id":"entity12","type":"wall","position":{"x":5,"y":0,"layer":0},"isInteractable":false},{"id":"entity13","type":"wall","position":{"x":6,"y":0,"layer":0},"isInteractable":false},{"id":"entity14","type":"wall","position":{"x":7,"y":0,"layer":0},"isInteractable":false},{"id":"entity15","type":"wall","position":{"x":0,"y":1,"layer":0},"isInteractable":false},{"id":"entity16","type":"wall","position":{"x":0,"y":2,"layer":0},"isInteractable":false},{"id":"entity17","type":"wall","position":{"x":0,"y":3,"layer":0},"isInteractable":false},{"id":"entity18","type":"wall","position":{"x":0,"y":4,"layer":0},"isInteractable":false},{"id":"entity19","type":"wall","position":{"x":0,"y":5,"layer":0},"isInteractable":false},{"id":"entity20","type":"wall","position":{"x":0,"y":6,"layer":0},"isInteractable":false},{"id":"entity21","type":"wall","position":{"x":0,"y":10,"layer":0},"isInteractable":false},{"id":"entity22","type":"wall","position":{"x":1,"y":10,"layer":0},"isInteractable":false},{"id":"entity23","type":"wall","position":{"x":2,"y":10,"layer":0},"isInteractable":false},{"id":"entity24","type":"wall","position":{"x":3,"y":10,"layer":0},"isInteractable":false},{"id":"entity25","type":"wall","position":{"x":4,"y":10,"layer":0},"isInteractable":false},{"id":"entity26","type":"wall","position":{"x":5,"y":10,"layer":0},"isInteractable":false},{"id":"entity27","type":"wall","position":{"x":6,"y":10,"layer":0},"isInteractable":false},{"id":"entity28","type":"wall","position":{"x":7,"y":10,"layer":0},"isInteractable":false},{"id":"entity29","type":"wall","position":{"x":7,"y":6,"layer":0},"isInteractable":false},{"id":"entity30","type":"wall","position":{"x":7,"y":5,"layer":0},"isInteractable":false},{"id":"entity31","type":"wall","position":{"x":7,"y":4,"layer":0},"isInteractable":false},{"id":"entity32","type":"wall","position":{"x":7,"y":3,"layer":0},"isInteractable":false},{"id":"entity33","type":"wall","position":{"x":7,"y":2,"layer":0},"isInteractable":false},{"id":"entity34","type":"wall","position":{"x":7,"y":1,"layer":0},"isInteractable":false},{"id":"entity35","type":"wall","position":{"x":0,"y":7,"layer":0},"isInteractable":false},{"id":"entity36","type":"wall","position":{"x":7,"y":7,"layer":0},"isInteractable":false},{"id":"entity37","type":"wall","position":{"x":0,"y":8,"layer":0},"isInteractable":false},{"id":"entity38","type":"wall","position":{"x":7,"y":8,"layer":0},"isInteractable":false},{"id":"entity39","type":"wall","position":{"x":0,"y":9,"layer":0},"isInteractable":false},{"id":"entity40","type":"wall","position":{"x":7,"y":9,"layer":0},"isInteractable":false},{"id":"entity41","type":"treasure","position":{"x":6,"y":1,"layer":0},"isInteractable":false},{"id":"entity42","type":"treasure","position":{"x":5,"y":1,"layer":0},"isInteractable":false},{"id":"entity0","type":"player","position":{"x":4,"y":2,"layer":0},"isInteractable":false,"attack":2,"health":9}],"inventory":[],"buildables":[],"goals":"","animations":[{"when":"PostTick","entityId":"entity0","queue":["translate-y -1","translate-y 1, over 0.4s","sprite player"],"loop":false,"duration":-1.0}],"entityCounter":44,"tickCounter":12,"keyStatus":true,"invisibilityPotionCounter":0,"invincibilityPotionCounter":0},{"dungeonId":"dungeon1","dungeonName":"testRoom","entities":[{"id":"entity1","type":"zombie_toast_spawner","position":{"x":3,"y":4,"layer":0},"isInteractable":true},{"id":"entity3","type":"sword","position":{"x":2,"y":2,"layer":0},"isInteractable":false,"attack":3,"durability":5},{"id":"entity6","type":"invincibility_potion","position":{"x":1,"y":2,"layer":0},"isInteractable":false},{"id":"entity7","type":"wall","position":{"x":0,"y":0,"layer":0},"isInteractable":false},{"id":"entity8","type":"wall","position":{"x":1,"y":0,"layer":0},"isInteractable":false},{"id":"entity9","type":"wall","position":{"x":2,"y":0,"layer":0},"isInteractable":false},{"id":"entity10","type":"wall","position":{"x":3,"y":0,"layer":0},"isInteractable":false},{"id":"entity11","type":"wall","position":{"x":4,"y":0,"layer":0},"isInteractable":false},{"id":"entity12","type":"wall","position":{"x":5,"y":0,"layer":0},"isInteractable":false},{"id":"entity13","type":"wall","position":{"x":6,"y":0,"layer":0},"isInteractable":false},{"id":"entity14","type":"wall","position":{"x":7,"y":0,"layer":0},"isInteractable":false},{"id":"entity15","type":"wall","position":{"x":0,"y":1,"layer":0},"isInteractable":false},{"id":"entity16","type":"wall","position":{"x":0,"y":2,"layer":0},"isInteractable":false},{"id":"entity17","type":"wall","position":{"x":0,"y":3,"layer":0},"isInteractable":false},{"id":"entity18","type":"wall","position":{"x":0,"y":4,"layer":0},"isInteractable":false},{"id":"entity19","type":"wall","position":{"x":0,"y":5,"layer":0},"isInteractable":false},{"id":"entity20","type":"wall","position":{"x":0,"y":6,"layer":0},"isInteractable":false},{"id":"entity21","type":"wall","position":{"x":0,"y":10,"layer":0},"isInteractable":false},{"id":"entity22","type":"wall","position":{"x":1,"y":10,"layer":0},"isInteractable":false},{"id":"entity23","type":"wall","position":{"x":2,"y":10,"layer":0},"isInteractable":false},{"id":"entity24","type":"wall","position":{"x":3,"y":10,"layer":0},"isInteractable":false},{"id":"entity25","type":"wall","position":{"x":4,"y":10,"layer":0},"isInteractable":false},{"id":"entity26","type":"wall","position":{"x":5,"y":10,"layer":0},"isInteractable":false},{"id":"entity27","type":"wall","position":{"x":6,"y":10,"layer":0},"isInteractable":false},{"id":"entity28","type":"wall","position":{"x":7,"y":10,"layer":0},"isInteractable":false},{"id":"entity29","type":"wall","position":{"x":7,"y":6,"layer":0},"isInteractable":false},{"id":"entity30","type":"wall","position":{"x":7,"y":5,"layer":0},"isInteractable":false},{"id":"entity31","type":"wall","position":{"x":7,"y":4,"layer":0},"isInteractable":false},{"id":"entity32","type":"wall","position":{"x":7,"y":3,"layer":0},"isInteractable":false},{"id":"entity33","type":"wall","position":{"x":7,"y":2,"layer":0},"isInteractable":false},{"id":"entity34","type":"wall","position":{"x":7,"y":1,"layer":0},"isInteractable":false},{"id":"entity35","type":"wall","position":{"x":0,"y":7,"layer":0},"isInteractable":false},{"id":"entity36","type":"wall","position":{"x":7,"y":7,"layer":0},"isInteractable":false},{"id":"entity37","type":"wall","position":{"x":0,"y":8,"layer":0},"isInteractable":false},{"id":"entity38","type":"wall","position":{"x":7,"y":8,"layer":0},"isInteractable":false},{"id":"entity39","type":"wall","position":{"x":0,"y":9,"layer":0},"isInteractable":false},{"id":"entity40","type":"wall","position":{"x":7,"y":9,"layer":0},"isInteractable":false},{"id":"entity41","type":"treasure","position":{"x":6,"y":1,"layer":0},"isInteractable":false},{"id":"entity42","type":"treasure","position":{"x":5,"y":1,"layer":0},"isInteractable":false},{"id":"entity0","type":"player","position":{"x":5,"y":2,"layer":0},"isInteractable":false,"attack":2,"health":9}],"inventory":[],"buildables":[],"goals":"","animations":[{"when":"PostTick","entityId":"entity0","queue":["translate-x -1","translate-x 1, over 0.4s","sprite player"],"loop":false,"duration":-1.0}],"entityCounter":44,"tickCounter":13,"keyStatus":true,"invisibilityPotionCounter":0,"invincibilityPotionCounter":0},{"dungeonId":"dungeon1","dungeonName":"testRoom","entities":[{"id":"entity1","type":"zombie_toast_spawner","position":{"x":3,"y":4,"layer":0},"isInteractable":true},{"id":"entity3","type":"sword","position":{"x":2,"y":2,"layer":0},"isInteractable":false,"attack":3,"durability":5},{"id":"entity6","type":"invincibility_potion","position":{"x":1,"y":2,"layer":0},"isInteractable":false},{"id":"entity7","type":"wall","position":{"x":0,"y":0,"layer":0},"isInteractable":false},{"id":"entity8","type":"wall","position":{"x":1,"y":0,"layer":0},"isInteractable":false},{"id":"entity9","type":"wall","position":{"x":2,"y":0,"layer":0},"isInteractable":false},{"id":"entity10","type":"wall","position":{"x":3,"y":0,"layer":0},"isInteractable":false},{"id":"entity11","type":"wall","position":{"x":4,"y":0,"layer":0},"isInteractable":false},{"id":"entity12","type":"wall","position":{"x":5,"y":0,"layer":0},"isInteractable":false},{"id":"entity13","type":"wall","position":{"x":6,"y":0,"layer":0},"isInteractable":false},{"id":"entity14","type":"wall","position":{"x":7,"y":0,"layer":0},"isInteractable":false},{"id":"entity15","type":"wall","position":{"x":0,"y":1,"layer":0},"isInteractable":false},{"id":"entity16","type":"wall","position":{"x":0,"y":2,"layer":0},"isInteractable":false},{"id":"entity17","type":"wall","position":{"x":0,"y":3,"layer":0},"isInteractable":false},{"id":"entity18","type":"wall","position":{"x":0,"y":4,"layer":0},"isInteractable":false},{"id":"entity19","type":"wall","position":{"x":0,"y":5,"layer":0},"isInteractable":false},{"id":"entity20","type":"wall","position":{"x":0,"y":6,"layer":0},"isInteractable":false},{"id":"entity21","type":"wall","position":{"x":0,"y":10,"layer":0},"isInteractable":false},{"id":"entity22","type":"wall","position":{"x":1,"y":10,"layer":0},"isInteractable":false},{"id":"entity23","type":"wall","position":{"x":2,"y":10,"layer":0},"isInteractable":false},{"id":"entity24","type":"wall","position":{"x":3,"y":10,"layer":0},"isInteractable":false},{"id":"entity25","type":"wall","position":{"x":4,"y":10,"layer":0},"isInteractable":false},{"id":"entity26","type":"wall","position":{"x":5,"y":10,"layer":0},"isInteractable":false},{"id":"entity27","type":"wall","position":{"x":6,"y":10,"layer":0},"isInteractable":false},{"id":"entity28","type":"wall","position":{"x":7,"y":10,"layer":0},"isInteractable":false},{"id":"entity29","type":"wall","position":{"x":7,"y":6,"layer":0},"isInteractable":false},{"id":"entity30","type":"wall","position":{"x":7,"y":5,"layer":0},"isInteractable":false},{"id":"entity31","type":"wall","position":{"x":7,"y":4,"layer":0},"isInteractable":false},{"id":"entity32","type":"wall","position":{"x":7,"y":3,"layer":0},"isInteractable":false},{"id":"entity33","type":"wall","position":{"x":7,"y":2,"layer":0},"isInteractable":false},{"id":"entity34","type":"wall","position":{"x":7,"y":1,"layer":0},"isInteractable":false},{"id":"entity35","type":"wall","position":{"x":0,"y":7,"layer":0},"isInteractable":false},{"id":"entity36","type":"wall","position":{"x":7,"y":7,"layer":0},"isInteractable":false},{"id":"entity37","type":"wall","position":{"x":0,"y":8,"layer":0},"isInteractable":false},{"id":"entity38","type":"wall","position":{"x":7,"y":8,"layer":0},"isInteractable":false},{"id":"entity39","type":"wall","position":{"x":0,"y":9,"layer":0},"isInteractable":false},{"id":"entity40","type":"wall","position":{"x":7,"y":9,"layer":0},"isInteractable":false},{"id":"entity41","type":"treasure","position":{"x":6,"y":1,"layer":0},"isInteractable":false},{"id":"entity0","type":"player","position":{"x":5,"y":1,"layer":0},"isInteractable":false,"attack":2,"health":9}],"inventory":[{"id":"entity42","type":"treasure"}],"buildables":[],"goals":"","animations":[{"when":"PostTick","entityId":"entity0","queue":["translate-y 1","translate-y -1, over 0.4s","sprite player"],"loop":false,"duration":-1.0}],"entityCounter":44,"tickCounter":14,"keyStatus":true,"invisibilityPotionCounter":0,"invincibilityPotionCounter":0},{"dungeonId":"dungeon1","dungeonName":"testRoom","entities":[{"id":"entity1","type":"zombie_toast_spawner","position":{"x":3,"y":4,"layer":0},"isInteractable":true},{"id":"entity3","type":"sword","position":{"x":2,"y":2,"layer":0},"isInteractable":false,"attack":3,"durability":5},{"id":"entity6","type":"invincibility_potion","position":{"x":1,"y":2,"layer":0},"isInteractable":false},{"id":"entity7","type":"wall","position":{"x":0,"y":0,"layer":0},"isInteractable":false},{"id":"entity8","type":"wall","position":{"x":1,"y":0,"layer":0},"isInteractable":false},{"id":"entity9","type":"wall","position":{"x":2,"y":0,"layer":0},"isInteractable":false},{"id":"entity10","type":"wall","position":{"x":3,"y":0,"layer":0},"isInteractable":false},{"id":"entity11","type":"wall","position":{"x":4,"y":0,"layer":0},"isInteractable":false},{"id":"entity12","type":"wall","position":{"x":5,"y":0,"layer":0},"isInteractable":false},{"id":"entity13","type":"wall","position":{"x":6,"y":0,"layer":0},"isInteractable":false},{"id":"entity14","type":"wall","position":{"x":7,"y":0,"layer":0},"isInteractable":false},{"id":"entity15","type":"wall","position":{"x":0,"y":1,"layer":0},"isInteractable":false},{"id":"entity16","type":"wall","position":{"x":0,"y":2,"layer":0},"isInteractable":false},{"id":"entity17","type":"wall","position":{"x":0,"y":3,"layer":0},"isInteractable":false},{"id":"entity18","type":"wall","position":{"x":0,"y":4,"layer":0},"isInteractable":false},{"id":"entity19","type":"wall","position":{"x":0,"y":5,"layer":0},"isInteractable":false},{"id":"entity20","type":"wall","position":{"x":0,"y":6,"layer":0},"isInteractable":false},{"id":"entity21","type":"wall","position":{"x":0,"y":10,"layer":0},"isInteractable":false},{"id":"entity22","type":"wall","position":{"x":1,"y":10,"layer":0},"isInteractable":false},{"id":"entity23","type":"wall","position":{"x":2,"y":10,"layer":0},"isInteractable":false},{"id":"entity24","type":"wall","position":{"x":3,"y":10,"layer":0},"isInteractable":false},{"id":"entity25","type":"wall","position":{"x":4,"y":10,"layer":0},"isInteractable":false},{"id":"entity26","type":"wall","position":{"x":5,"y":10,"layer":0},"isInteractable":false},{"id":"entity27","type":"wall","position":{"x":6,"y":10,"layer":0},"isInteractable":false},{"id":"entity28","type":"wall","position":{"x":7,"y":10,"layer":0},"isInteractable":false},{"id":"entity29","type":"wall","position":{"x":7,"y":6,"layer":0},"isInteractable":false},{"id":"entity30","type":"wall","position":{"x":7,"y":5,"layer":0},"isInteractable":false},{"id":"entity31","type":"wall","position":{"x":7,"y":4,"layer":0},"isInteractable":false},{"id":"entity32","type":"wall","position":{"x":7,"y":3,"layer":0},"isInteractable":false},{"id":"entity33","type":"wall","position":{"x":7,"y":2,"layer":0},"isInteractable":false},{"id":"entity34","type":"wall","position":{"x":7,"y":1,"layer":0},"isInteractable":false},{"id":"entity35","type":"wall","position":{"x":0,"y":7,"layer":0},"isInteractable":false},{"id":"entity36","type":"wall","position":{"x":7,"y":7,"layer":0},"isInteractable":false},{"id":"entity37","type":"wall","position":{"x":0,"y":8,"layer":0},"isInteractable":false},{"id":"entity38","type":"wall","position":{"x":7,"y":8,"layer":0},"isInteractable":false},{"id":"entity39","type":"wall","position":{"x":0,"y":9,"layer":0},"isInteractable":false},{"id":"entity40","type":"wall","position":{"x":7,"y":9,"layer":0},"isInteractable":false},{"id":"entity0","type":"player","position":{"x":6,"y":1,"layer":0},"isInteractable":false,"attack":2,"health":9}],"inventory":[{"id":"entity42","type":"treasure"},{"id":"entity41","type":"treasure"}],"buildables":[],"goals":"","animations":[{"when":"PostTick","entityId":"entity0","queue":["translate-x -1","translate-x 1, over 0.4s","sprite player"],"loop":false,"duration":-1.0}],"entityCounter":44,"tickCounter":15,"keyStatus":true,"invisibilityPotionCounter":0,"invincibilityPotionCounter":0},{"dungeonId":"dungeon1","dungeonName":"testRoom","entities":[{"id":"entity1","type":"zombie_toast_spawner","position":{"x":3,"y":4,"layer":0},"isInteractable":true},{"id":"entity3","type":"sword","position":{"x":2,"y":2,"layer":0},"isInteractable":false,"attack":3,"durability":5},{"id":"entity6","type":"invincibility_potion","position":{"x":1,"y":2,"layer":0},"isInteractable":false},{"id":"entity7","type":"wall","position":{"x":0,"y":0,"layer":0},"isInteractable":false},{"id":"entity8","type":"wall","position":{"x":1,"y":0,"layer":0},"isInteractable":false},{"id":"entity9","type":"wall","position":{"x":2,"y":0,"layer":0},"isInteractable":false},{"id":"entity10","type":"wall","position":{"x":3,"y":0,"layer":0},"isInteractable":false},{"id":"entity11","type":"wall","position":{"x":4,"y":0,"layer":0},"isInteractable":false},{"id":"entity12","type":"wall","position":{"x":5,"y":0,"layer":0},"isInteractable":false},{"id":"entity13","type":"wall","position":{"x":6,"y":0,"layer":0},"isInteractable":false},{"id":"entity14","type":"wall","position":{"x":7,"y":0,"layer":0},"isInteractable":false},{"id":"entity15","type":"wall","position":{"x":0,"y":1,"layer":0},"isInteractable":false},{"id":"entity16","type":"wall","position":{"x":0,"y":2,"layer":0},"isInteractable":false},{"id":"entity17","type":"wall","position":{"x":0,"y":3,"layer":0},"isInteractable":false},{"id":"entity18","type":"wall","position":{"x":0,"y":4,"layer":0},"isInteractable":false},{"id":"entity19","type":"wall","position":{"x":0,"y":5,"layer":0},"isInteractable":false},{"id":"entity20","type":"wall","position":{"x":0,"y":6,"layer":0},"isInteractable":false},{"id":"entity21","type":"wall","position":{"x":0,"y":10,"layer":0},"isInteractable":false},{"id":"entity22","type":"wall","position":{"x":1,"y":10,"layer":0},"isInteractable":false},{"id":"entity23","type":"wall","position":{"x":2,"y":10,"layer":0},"isInteractable":false},{"id":"entity24","type":"wall","position":{"x":3,"y":10,"layer":0},"isInteractable":false},{"id":"entity25","type":"wall","position":{"x":4,"y":10,"layer":0},"isInteractable":false},{"id":"entity26","type":"wall","position":{"x":5,"y":10,"layer":0},"isInteractable":false},{"id":"entity27","type":"wall","position":{"x":6,"y":10,"layer":0},"isInteractable":false},{"id":"entity28","type":"wall","position":{"x":7,"y":10,"layer":0},"isInteractable":false},{"id":"entity29","type":"wall","position":{"x":7,"y":6,"layer":0},"isInteractable":false},{"id":"entity30","type":"wall","position":{"x":7,"y":5,"layer":0},"isInteractable":false},{"id":"entity31","type":"wall","position":{"x":7,"y":4,"layer":0},"isInteractable":false},{"id":"entity32","type":"wall","position":{"x":7,"y":3,"layer":0},"isInteractable":false},{"id":"entity33","type":"wall","position":{"x":7,"y":2,"layer":0},"isInteractable":false},{"id":"entity34","type":"wall","position":{"x":7,"y":1,"layer":0},"isInteractable":false},{"id":"entity35","type":"wall","position":{"x":0,"y":7,"layer":0},"isInteractable":false},{"id":"entity36","type":"wall","position":{"x":7,"y":7,"layer":0},"isInteractable":false},{"id":"entity37","type":"wall","position":{"x":0,"y":8,"layer":0},"isInteractable":false},{"id":"entity38","type":"wall","position":{"x":7,"y":8,"layer":0},"isInteractable":false},{"id":"entity39","type":"wall","position":{"x":0,"y":9,"layer":0},"isInteractable":false},{"id":"entity40","type":"wall","position":{"x":7,"y":9,"layer":0},"isInteractable":false},{"id":"entity0","type":"player","position":{"x":6,"y":2,"layer":0},"isInteractable":false,"attack":2,"health":9}],"inventory":[{"id":"entity42","type":"treasure"},{"id":"entity41","type":"treasure"}],"buildables":[],"goals":"","animations":[{"when":"PostTick","entityId":"entity0","queue":["translate-y -1","translate-y 1, over 0.4s","sprite player"],"loop":false,"duration":-1.0}],"entityCounter":44,"tickCounter":16,"keyStatus":true,"invisibilityPotionCounter":0,"invincibilityPotionCounter":0},{"dungeonId":"dungeon1","dungeonName":"testRoom","entities":[{"id":"entity1","type":"zombie_toast_spawner","position":{"x":3,"y":4,"layer":0},"isInteractable":true},{"id":"entity3","type":"sword","position":{"x":2,"y":2,"layer":0},"isInteractable":false,"attack":3,"durability":5},{"id":"entity6","type":"invincibility_potion","position":{"x":1,"y":2,"layer":0},"isInteractable":false},{"id":"entity7","type":"wall","position":{"x":0,"y":0,"layer":0},"isInteractable":false},{"id":"entity8","type":"wall","position":{"x":1,"y":0,"layer":0},"isInteractable":false},{"id":"entity9","type":"wall","position":{"x":2,"y":0,"layer":0},"isInteractable":false},{"id":"entity10","type":"wall","position":{"x":3,"y":0,"layer":0},"isInteractable":false},{"id":"entity11","type":"wall","position":{"x":4,"y":0,"layer":0},"isInteractable":false},{"id":"entity12","type":"wall","position":{"x":5,"y":0,"layer":0},"isInteractable":false},{"id":"entity13","type":"wall","position":{"x":6,"y":0,"layer":0},"isInteractable":false},{"id":"entity14","type":"wall","position":{"x":7,"y":0,"layer":0},"isInteractable":false},{"id":"entity15","type":"wall","position":{"x":0,"y":1,"layer":0},"isInteractable":false},{"id":"entity16","type":"wall","position":{"x":0,"y":2,"layer":0},"isInteractable":false},{"id":"entity17","type":"wall","position":{"x":0,"y":3,"layer":0},"isInteractable":false},{"id":"entity18","type":"wall","position":{"x":0,"y":4,"layer":0},"isInteractable":false},{"id":"entity19","type":"wall","position":{"x":0,"y":5,"layer":0},"isInteractable":false},{"id":"entity20","type":"wall","position":{"x":0,"y":6,"layer":0},"isInteractable":false},{"id":"entity21","type":"wall","position":{"x":0,"y":10,"layer":0},"isInteractable":false},{"id":"entity22","type":"wall","position":{"x":1,"y":10,"layer":0},"isInteractable":false},{"id":"entity23","type":"wall","position":{"x":2,"y":10,"layer":0},"isInteractable":false},{"id":"entity24","type":"wall","position":{"x":3,"y":10,"layer":0},"isInteractable":false},{"id":"entity25","type":"wall","position":{"x":4,"y":10,"layer":0},"isInteractable":false},{"id":"entity26","type":"wall","position":{"x":5,"y":10,"layer":0},"isInteractable":false},{"id":"entity27","type":"wall","position":{"x":6,"y":10,"layer":0},"isInteractable":false},{"id":"entity28","type":"wall","position":{"x":7,"y":10,"layer":0},"isInteractable":false},{"id":"entity29","type":"wall","position":{"x":7,"y":6,"layer":0},"isInteractable":false},{"id":"entity30","type":"wall","position":{"x":7,"y":5,"layer":0},"isInteractable":false},{"id":"entity31","type":"wall","position":{"x":7,"y":4,"layer":0},"isInteractable":false},{"id":"entity32","type":"wall","position":{"x":7,"y":3,"layer":0},"isInteractable":false},{"id":"entity33","type":"wall","position":{"x":7,"y":2,"layer":0},"isInteractable":false},{"id":"entity34","type":"wall","position":{"x":7,"y":1,"layer":0},"isInteractable":false},{"id":"entity35","type":"wall","position":{"x":0,"y":7,"layer":0},"isInteractable":false},{"id":"entity36","type":"wall","position":{"x":7,"y":7,"layer":0},"isInteractable":false},{"id":"entity37","type":"wall","position":{"x":0,"y":8,"layer":0},"isInteractable":false},{"id":"entity38","type":"wall","position":{"x":7,"y":8,"layer":0},"isInteractable":false},{"id":"entity39","type":"wall","position":{"x":0,"y":9,"layer":0},"isInteractable":false},{"id":"entity40","type":"wall","position":{"x":7,"y":9,"layer":0},"isInteractable":false},{"id":"entity0","type":"player","position":{"x":5,"y":2,"layer":0},"isInteractable":false,"attack":2,"health":9}],"inventory":[{"id":"entity42","type":"treasure"},{"id":"entity41","type":"treasure"}],"buildables":[],"goals":"","animations":[{"when":"PostTick","entityId":"entity0","queue":["translate-x 1","translate-x -1, over 0.4s","sprite player"],"loop":false,"duration":-1.0}],"entityCounter":44,"tickCounter":17,"keyStatus":true,"invisibilityPotionCounter":0,"invincibilityPotionCounter":0}]